msrpcs/__init__.py
msrpcs/ept.py
msrpcs/mc_ccfg.py
msrpcs/mc_iisa.py
msrpcs/mc_mqac.py
msrpcs/mgmt.py
msrpcs/ms_adtg.py
msrpcs/ms_adts_Claims.py
msrpcs/ms_bkrp.py
msrpcs/ms_bpau.py
msrpcs/ms_brwsa.py
msrpcs/ms_capr.py
msrpcs/ms_cmpo.py
msrpcs/ms_cmrp_clusapi2.py
msrpcs/ms_cmrp_clusapi3.py
msrpcs/ms_com.py
msrpcs/ms_coma.py
msrpcs/ms_comev.py
msrpcs/ms_comt.py
msrpcs/ms_csra.py
msrpcs/ms_csvp.py
msrpcs/ms_dcom.py
msrpcs/ms_dfsnm.py
msrpcs/ms_dfsrh.py
msrpcs/ms_dhcpm.py
msrpcs/ms_dltm.py
msrpcs/ms_dltw.py
msrpcs/ms_dmrp_dmintf.py
msrpcs/ms_dmrp_dmintf3.py
msrpcs/ms_dnsp.py
msrpcs/ms_drsr.py
msrpcs/ms_dssp.py
msrpcs/ms_dtyp.py
msrpcs/ms_eerr.py
msrpcs/ms_efsr.py
msrpcs/ms_even.py
msrpcs/ms_even6.py
msrpcs/ms_fasp.py
msrpcs/ms_fax_fax.py
msrpcs/ms_fax_faxclient.py
msrpcs/ms_fax_faxdatatypes.py
msrpcs/ms_frs1_frsapi.py
msrpcs/ms_frs1_frsrpc.py
msrpcs/ms_frs2.py
msrpcs/ms_fsrm.py
msrpcs/ms_fsrvp.py
msrpcs/ms_gkdi.py
msrpcs/ms_icpr.py
msrpcs/ms_iiss.py
msrpcs/ms_imsa.py
msrpcs/ms_ioi.py
msrpcs/ms_irp.py
msrpcs/ms_lrec.py
msrpcs/ms_lsad.py
msrpcs/ms_lsat.py
msrpcs/ms_mqds.py
msrpcs/ms_mqmp.py
msrpcs/ms_mqmq.py
msrpcs/ms_mqmr.py
msrpcs/ms_mqqp.py
msrpcs/ms_mqrr.py
msrpcs/ms_msrp_msgsvc.py
msrpcs/ms_msrp_msgsvcsend.py
msrpcs/ms_nrpc.py
msrpcs/ms_nspi.py
msrpcs/ms_oaut.py
msrpcs/ms_ocspa.py
msrpcs/ms_oxabref.py
msrpcs/ms_oxcrpc.py
msrpcs/ms_oxnspi.py
msrpcs/ms_pac.py
msrpcs/ms_par.py
msrpcs/ms_pcq.py
msrpcs/ms_pla.py
msrpcs/ms_raa.py
msrpcs/ms_rai.py
msrpcs/ms_raiw_winsif.py
msrpcs/ms_raiw_winsif2.py
msrpcs/ms_rdpesc.py
msrpcs/ms_rpce.py
msrpcs/ms_rpcl.py
msrpcs/ms_rprn.py
msrpcs/ms_rrasm.py
msrpcs/ms_rrp.py
msrpcs/ms_rsmp.py
msrpcs/ms_rsp_initshutdown.py
msrpcs/ms_rsp_windowsshutdown.py
msrpcs/ms_rsp_winreg.py
msrpcs/ms_samr.py
msrpcs/ms_scmp.py
msrpcs/ms_scmr.py
msrpcs/ms_srvs.py
msrpcs/ms_ssp.py
msrpcs/ms_swn.py
msrpcs/ms_tpmvsc.py
msrpcs/ms_tsch_ATSvc.py
msrpcs/ms_tsch_SaSecRpc.py
msrpcs/ms_tsch_SchRpc.py
msrpcs/ms_tsgu.py
msrpcs/ms_tsrap.py
msrpcs/ms_tsts_SessEnvRpc.py
scapy_rpc-0.0.1.dist-info/METADATA
scapy_rpc-0.0.1.dist-info/WHEEL
scapy_rpc-0.0.1.dist-info/top_level.txt
scapy_rpc-0.0.1.dist-info/RECORD
