Metadata-Version: 2.4
Name: scapy-rpc
Version: 0.0.1
Summary: Scapy RPC definitions
Classifier: License :: OSI Approved :: GNU General Public License v2 (GPLv2)
Requires-Python: <4,>=3.7
